<?xml version="1.0" encoding="UTF-8" standalone="yes"?>
<xdr:wsDr xmlns:xdr="http://schemas.openxmlformats.org/drawingml/2006/spreadsheetDrawing" xmlns:a="http://schemas.openxmlformats.org/drawingml/2006/main"><xdr:twoCellAnchor><xdr:from><xdr:col>0</xdr:col><xdr:colOff>295275</xdr:colOff><xdr:row>1</xdr:row><xdr:rowOff>104774</xdr:rowOff></xdr:from><xdr:to><xdr:col>1</xdr:col><xdr:colOff>590550</xdr:colOff><xdr:row>4</xdr:row><xdr:rowOff>9524</xdr:rowOff></xdr:to><xdr:sp macro="" textlink=""><xdr:nvSpPr><xdr:cNvPr id="2" name="TextBox 1"/><xdr:cNvSpPr txBox="1"/></xdr:nvSpPr><xdr:spPr><a:xfrm><a:off x="295275" y="295274"/><a:ext cx="628650" cy="657225"/></a:xfrm><a:prstGeom prst="rect"><a:avLst/></a:prstGeom><a:noFill/><a:ln w="9525" cmpd="sng"><a:noFill/></a:ln></xdr:spPr><xdr:style><a:lnRef idx="0"><a:scrgbClr r="0" g="0" b="0"/></a:lnRef><a:fillRef idx="0"><a:scrgbClr r="0" g="0" b="0"/></a:fillRef><a:effectRef idx="0"><a:scrgbClr r="0" g="0" b="0"/></a:effectRef><a:fontRef idx="minor"><a:schemeClr val="dk1"/></a:fontRef></xdr:style><xdr:txBody><a:bodyPr vertOverflow="clip" horzOverflow="clip" wrap="square" rtlCol="0" anchor="t"/><a:lstStyle/><a:p><a:r><a:rPr lang="en-US" sz="1200"><a:latin typeface="+mn-lt"/></a:rPr><a:t>Nama</a:t></a:r></a:p><a:p><a:r><a:rPr lang="en-US" sz="1200"><a:latin typeface="+mn-lt"/></a:rPr><a:t>NPM</a:t></a:r></a:p><a:p><a:r><a:rPr lang="en-US" sz="1200"><a:latin typeface="+mn-lt"/></a:rPr><a:t>Kelas</a:t></a:r></a:p></xdr:txBody></xdr:sp><xdr:clientData/></xdr:twoCellAnchor><xdr:twoCellAnchor><xdr:from><xdr:col>1</xdr:col><xdr:colOff>438149</xdr:colOff><xdr:row>1</xdr:row><xdr:rowOff>104774</xdr:rowOff></xdr:from><xdr:to><xdr:col>2</xdr:col><xdr:colOff>1200149</xdr:colOff><xdr:row>4</xdr:row><xdr:rowOff>9524</xdr:rowOff></xdr:to><xdr:sp macro="" textlink=""><xdr:nvSpPr><xdr:cNvPr id="3" name="TextBox 2"/><xdr:cNvSpPr txBox="1"/></xdr:nvSpPr><xdr:spPr><a:xfrm><a:off x="771524" y="295274"/><a:ext cx="2733675" cy="685800"/></a:xfrm><a:prstGeom prst="rect"><a:avLst/></a:prstGeom><a:noFill/><a:ln w="9525" cmpd="sng"><a:noFill/></a:ln></xdr:spPr><xdr:style><a:lnRef idx="0"><a:scrgbClr r="0" g="0" b="0"/></a:lnRef><a:fillRef idx="0"><a:scrgbClr r="0" g="0" b="0"/></a:fillRef><a:effectRef idx="0"><a:scrgbClr r="0" g="0" b="0"/></a:effectRef><a:fontRef idx="minor"><a:schemeClr val="dk1"/></a:fontRef></xdr:style><xdr:txBody><a:bodyPr vertOverflow="clip" horzOverflow="clip" wrap="square" rtlCol="0" anchor="t"/><a:lstStyle/><a:p><a:r><a:rPr lang="en-US" sz="1200"><a:latin typeface="+mn-lt"/></a:rPr><a:t>:</a:t></a:r><a:r><a:rPr lang="en-US" sz="1200" baseline="0"><a:latin typeface="+mn-lt"/></a:rPr><a:t> Isep Lutpi Nur</a:t></a:r><a:endParaRPr lang="en-US" sz="1200"><a:latin typeface="+mn-lt"/></a:endParaRPr></a:p><a:p><a:r><a:rPr lang="en-US" sz="1200"><a:latin typeface="+mn-lt"/></a:rPr><a:t>: 2113191079</a:t></a:r></a:p><a:p><a:pPr marL="0" marR="0" lvl="0" indent="0" defTabSz="914400" eaLnBrk="1" fontAlgn="auto" latinLnBrk="0" hangingPunct="1"><a:lnSpc><a:spcPct val="100000"/></a:lnSpc><a:spcBef><a:spcPts val="0"/></a:spcBef><a:spcAft><a:spcPts val="0"/></a:spcAft><a:buClrTx/><a:buSzTx/><a:buFontTx/><a:buNone/><a:tabLst/><a:defRPr/></a:pPr><a:r><a:rPr lang="en-US" sz="1200"><a:latin typeface="+mn-lt"/></a:rPr><a:t>: </a:t></a:r><a:r><a:rPr lang="en-US" sz="1100"><a:solidFill><a:schemeClr val="dk1"/></a:solidFill><a:effectLst/><a:latin typeface="+mn-lt"/><a:ea typeface="+mn-ea"/><a:cs typeface="+mn-cs"/></a:rPr><a:t>S1 Teknik Informatika A2 2019</a:t></a:r><a:endParaRPr lang="en-US" sz="1200"><a:effectLst/></a:endParaRPr></a:p><a:p><a:endParaRPr lang="en-US" sz="1200"><a:latin typeface="+mn-lt"/></a:endParaRPr></a:p></xdr:txBody></xdr:sp><xdr:clientData/></xdr:twoCellAnchor></xdr:wsDr>